README.txt
setup.py
Products/__init__.py
Products.PurgeMissingObjectInterfaces.egg-info/#SOURCES.txt#
Products.PurgeMissingObjectInterfaces.egg-info/PKG-INFO
Products.PurgeMissingObjectInterfaces.egg-info/SOURCES.txt
Products.PurgeMissingObjectInterfaces.egg-info/SOURCES.txt~
Products.PurgeMissingObjectInterfaces.egg-info/dependency_links.txt
Products.PurgeMissingObjectInterfaces.egg-info/entry_points.txt
Products.PurgeMissingObjectInterfaces.egg-info/namespace_packages.txt
Products.PurgeMissingObjectInterfaces.egg-info/not-zip-safe
Products.PurgeMissingObjectInterfaces.egg-info/requires.txt
Products.PurgeMissingObjectInterfaces.egg-info/top_level.txt
Products/PurgeMissingObjectInterfaces/__init__.py
Products/PurgeMissingObjectInterfaces/changes.txt
Products/PurgeMissingObjectInterfaces/interfaces.py
Products/PurgeMissingObjectInterfaces/old__init__.py
Products/PurgeMissingObjectInterfaces/readme.txt
Products/PurgeMissingObjectInterfaces/Extensions/__init__.py
Products/PurgeMissingObjectInterfaces/Extensions/broken.py
Products/PurgeMissingObjectInterfaces/Extensions/find.py