Metadata-Version: 1.0
Name: Products.PurgeMissingObjectInterfaces
Version: 1.0.4a
Summary: A product for purging old and missing marker interfaces from objects
Home-page: http://www.nidelven-it.no/d
Author: Morten W. Petersen
Author-email: info@nidelven-it.no
License: GPL
Keywords: python zope interfaces plone silva developers
Platform: UNKNOWN
Classifier: Programming Language :: Python
Classifier: Framework :: Zope2
Classifier: Framework :: ZODB
Classifier: Development Status :: 3 - Alpha
Classifier: Framework :: Plone
Classifier: Intended Audience :: Developers
Classifier: License :: OSI Approved :: GNU General Public License (GPL)
Classifier: Operating System :: OS Independent
Classifier: Topic :: Database
Classifier: Topic :: Software Development :: Debuggers
Classifier: Topic :: Utilities
